jaccount_auth/__init__.py
jaccount_auth/ascii.py
jaccount_auth/asyncio.py
jaccount_auth-0.0.1.dist-info/LICENSE
jaccount_auth-0.0.1.dist-info/METADATA
jaccount_auth-0.0.1.dist-info/WHEEL
jaccount_auth-0.0.1.dist-info/top_level.txt
jaccount_auth-0.0.1.dist-info/RECORD
