Metadata-Version: 2.1
Name: jaccount-auth
Version: 0.0.1
Summary: A small plugin to help use jaccount login in python programs.
Home-page: https://github.com/linsyking/jaccount-auth
Author: linsyking
Author-email: xiangyiming2002@gmail.com
Maintainer: linsyking
Maintainer-email: xiangyiming2002@gmail.com
License: MIT
Project-URL: Bug Reports, https://github.com/linsyking/jaccount-auth/issues
Project-URL: Source, https://github.com/linsyking/jaccount-auth
License-File: LICENSE
Requires-Dist: aiohttp
Requires-Dist: beautifulsoup4
Requires-Dist: pillow
